{"singlePage": [], "startSite": "09/26/2024", "filingNum": "", "onePageListNum": 15, "commentLabelColor": "#006b75", "yearColorList": ["#bc4c00", "#0969da", "#1f883d", "#A333D0"], "i18n": "CN", "themeMode": "manual", "dayTheme": "light", "nightTheme": "dark", "urlMode": "pinyin", "script": "<script src='https://blog.meekdai.com/Gmeek/plugins/lightbox.js'></script>", "style": "", "head": "", "indexScript": "", "indexStyle": "", "bottomText": "", "showPostSource": 1, "iconList": {}, "UTC": 8, "rssSplit": "sentence", "exlink": {}, "needComment": 1, "allHead": "<script src='https://blog.meekdai.com/Gmeek/plugins/GmeekBSZ.js'></script>", "title": "\u5927\u60a6\u60a6\u7684\u535a\u5ba2", "subTitle": "\u6211\u9700\u8981\u4f11\u606f", "avatarUrl": "https://github.com/liyue260/blog/raw/main/img/avatar.svg", "GMEEK_VERSION": "last", "faviconUrl": "https://github.com/liyue260/blog/raw/main/img/favicon.svg", "postListJson": {"P3": {"htmlDir": "docs/post/shi-yong-Gmeek-cong-ling-da-jian-bing-shi-yong-yi-ge-bo-ke.html", "labels": ["\u535a\u5ba2"], "postTitle": "\u4f7f\u7528Gmeek\u4ece\u96f6\u642d\u5efa\u5e76\u4f7f\u7528\u4e00\u4e2a\u535a\u5ba2", "postUrl": "post/shi-yong-Gmeek-cong-ling-da-jian-bing-shi-yong-yi-ge-bo-ke.html", "postSourceUrl": "https://github.com/liyue260/blog/issues/3", "commentNum": 0, "wordCount": 705, "description": "### \u642d\u5efa\r\n\r\n - [Gmeek\u5feb\u901f\u4e0a\u624b](https://blog.meekdai.com/post/Gmeek-kuai-su-shang-shou.html)\r\n - \u6dfb\u52a0\u81ea\u5df1\u7684\u5934\u50cf\r\n        1. \u5148\u5c06\u5934\u50cf\u8f6c\u6362\u6210 **svg** \u683c\u5f0f\uff0c\u597d\u50cf Gmeek \u53ea\u652f\u6301\u8fd9\u79cd\u683c\u5f0f\r\n        2. \u628a\u5934\u50cf\u6587\u4ef6\u4e0a\u4f20\u5230 github \u4ed3\u5e93\u5185\r\n        3. \u6253\u5f00\u5934\u50cf\u6587\u4ef6\u9875\uff0c\u5c06\u5730\u5740\u680f\u4e2d\u7684 \u201c**blob**\u201d \u66f4\u6539\u4e3a '**raw**' \u5e76\u590d\u5236\u66f4\u6539\u540e\u7684\u94fe\u63a5\r\n        4. \u7c98\u8d34\u521a\u521a\u590d\u5236\u7684\u5185\u5bb9\u5230 config.json \u7684 'avatarUrl' \u540e\r\n        5. Action>build Gmeek>Run workflow\r\n\r\n### \u4f7f\u7528 tips\r\n-  [\u57fa\u672c\u64b0\u5199\u548c\u683c\u5f0f\u8bed\u6cd5](https://docs.github.com/zh/get-started/writing-on-github/getting-started-with-writing-and-formatting-on-github/basic-writing-and-formatting-syntax)\r\n- [\u4e2d\u6587\u535a\u5ba2\u6392\u7248\u6307\u5357](https://github.com/qianguyihao/document-guide)\r\n- [\u3010Gmeek\u8fdb\u9636\u3011\u5f3a\u8c03\u5173\u952e\u4fe1\u606f\u4f7f\u7528](https://blog.meekdai.com/post/%E3%80%90Gmeek-jin-jie-%E3%80%91-qiang-diao-guan-jian-xin-xi-shi-yong.html)\r\n\u3002", "top": 0, "createdAt": 1727354089, "style": "", "script": "<script src='https://blog.meekdai.com/Gmeek/plugins/lightbox.js'></script>", "head": "", "ogImage": "https://github.com/liyue260/blog/raw/main/img/avatar.svg", "createdDate": "2024-09-26", "dateLabelColor": "#bc4c00"}, "P6": {"htmlDir": "docs/post/chang-yong-ruan-jian.html", "labels": ["\u8d44\u6e90"], "postTitle": "\u5e38\u7528\u8f6f\u4ef6", "postUrl": "post/chang-yong-ruan-jian.html", "postSourceUrl": "https://github.com/liyue260/blog/issues/6", "commentNum": 0, "wordCount": 452, "description": "- \u767e\u5ea6\u7f51\u76d8\u5408\u79df \r\n[\u6211\u7231\u767d\u5ad6](https://feizhu.3kla.top/assets/img/default/)  \u8fdb\u5165 Anran \u6742\u8d27\u94fa\r\n\r\n- [DiskGenius \u7834\u89e3\u4e13\u4e1a\u7248\u5408\u8f91](https://weilining.github.io/251.html) \r\n\r\n- PS4\u7834\u89e3\u6e38\u620f\u4e0b\u8f7d\r\n   [Gkinto](https://www.gkinto.com/category/ps4)\r\n   [\u5168\u7403\u6e38\u620f\u767d\u5ad6\u7f51](https://www.520switch.com/ps4/)\r\n   [\u5965\u5fb7\u5f6a\u8ba1\u5212](https://2468c.com/)\r\n   PS4\u5929\u7ffc\u8d44\u6e90\u94fe\u63a5\uff1ahttps://cloud.189.cn/t/7BbmuuJJ7Nfu \uff08\u8bbf\u95ee\u7801\uff1a4lrt\uff09\r\n   \u5929\u7ffcPS4\u8d44\u6e90\u76ee\u5f55\u94fe\u63a5https://cloud.189.cn/t/UjMZJ3EnMfya \uff08\u8bbf\u95ee\u7801\uff1a8eyh\uff09\r\n  \r\n- [\u89e3\u538b\u7f29\u8f6f\u4ef6 7-Zip](https://www.7-zip.org/)\u3002", "top": 0, "createdAt": 1727703458, "style": "", "script": "<script src='https://blog.meekdai.com/Gmeek/plugins/lightbox.js'></script>", "head": "", "ogImage": "https://github.com/liyue260/blog/raw/main/img/avatar.svg", "createdDate": "2024-09-30", "dateLabelColor": "#bc4c00"}, "P7": {"htmlDir": "docs/post/Code-gong-ju.html", "labels": ["\u8d44\u6e90"], "postTitle": "Code\u5de5\u5177", "postUrl": "post/Code-gong-ju.html", "postSourceUrl": "https://github.com/liyue260/blog/issues/7", "commentNum": 0, "wordCount": 48, "description": "- \u53d8\u91cf\u547d\u540d [CODELF](https://unbug.github.io/codelf/)\u3002", "top": 0, "createdAt": 1727875478, "style": "", "script": "<script src='https://blog.meekdai.com/Gmeek/plugins/lightbox.js'></script>", "head": "", "ogImage": "https://github.com/liyue260/blog/raw/main/img/avatar.svg", "createdDate": "2024-10-02", "dateLabelColor": "#bc4c00"}}, "singeListJson": {}, "labelColorDict": {"\u535a\u5ba2": "#d4c5f9", "\u8d44\u6e90": "#c5def5"}, "displayTitle": "\u5927\u60a6\u60a6\u7684\u535a\u5ba2", "ogImage": "https://github.com/liyue260/blog/raw/main/img/avatar.svg", "primerCSS": "<link href='https://mirrors.sustech.edu.cn/cdnjs/ajax/libs/Primer/21.0.7/primer.css' rel='stylesheet' />", "homeUrl": "https://liyue260.github.io/blog", "prevUrl": "disabled", "nextUrl": "disabled"}